Metadata-Version: 2.1
Name: fastapi-middleware-logger
Version: 0.0.5
Summary: Simple library to customize logger for FastAPI
Home-page: https://github.com/pauldechorgnat/fastapi-custom-logger
Author: Paul Déchorgnat
Author-email: paul.dechorgnat@gmail.com
License: MIT
Platform: UNKNOWN
Classifier: Framework :: FastAPI
License-File: LICENSE
